leslieDelury/__init__.py
leslieDelury/popEstimate.py
Leslie_DeLury-0.0.2.dist-info/LICENSE
Leslie_DeLury-0.0.2.dist-info/METADATA
Leslie_DeLury-0.0.2.dist-info/WHEEL
Leslie_DeLury-0.0.2.dist-info/top_level.txt
Leslie_DeLury-0.0.2.dist-info/RECORD
