Metadata-Version: 2.1
Name: Leslie-DeLury
Version: 0.0.2
Summary: A python package to calculate the Leslie-Delury population estimate.
Home-page: https://github.com/orectique/lesliedelury
Author: Sreehari Pulickamadhom Sreedhar
Author-email: orectique@gmail.com
License: UNKNOWN
Project-URL: Bug Tracker, https://github.com/orectique/LeslieDeLury/issues
Platform: UNKNOWN
Classifier: Programming Language :: Python :: 3
Classifier: License :: OSI Approved :: MIT License
Classifier: Operating System :: OS Independent
Requires-Python: >=3.6
License-File: LICENSE
